LICENSE.txt
MANIFEST.in
README.rst
setup.py
django_improved_inlines.egg-info/PKG-INFO
django_improved_inlines.egg-info/SOURCES.txt
django_improved_inlines.egg-info/dependency_links.txt
django_improved_inlines.egg-info/requires.txt
django_improved_inlines.egg-info/top_level.txt
improved_inlines/__init__.py
improved_inlines/models.py
improved_inlines/parser.py
improved_inlines/templatetags/__init__.py
improved_inlines/templatetags/inlines.py