Metadata-Version: 1.1
Name: django-improved-inlines
Version: 0.2.2
Summary: Inline object rendering for django, based on django-basic-apps + filters + templates
Home-page: http://github.com/issackelly/django-improved-inlines
Author: Issac Kelly
Author-email: issac@kellycreativetech.com
License: BSD
Platform: UNKNOWN
Classifier: Development Status :: 4 - Beta
Classifier: Framework :: Django
Classifier: Intended Audience :: Developers
Classifier: License :: OSI Approved :: BSD License
Classifier: Operating System :: OS Independent
Classifier: Programming Language :: Python
Classifier: Topic :: Internet :: WWW/HTTP
Requires: BeautifulSoup
